AddUsers.py
__init__.py
auth/GoogleAuth.py
auth/__init__.py
lib/CreateLabel.py
lib/__init__.py
crmcontactrollingmachine-0.0.1.dist-info/METADATA
crmcontactrollingmachine-0.0.1.dist-info/WHEEL
crmcontactrollingmachine-0.0.1.dist-info/licenses/LICENSE.chromedriver
crmcontactrollingmachine-0.0.1.dist-info/licenses/LICENSE.txt
crmcontactrollingmachine-0.0.1.dist-info/RECORD
